upstash_semantic_cache/__init__.py
upstash_semantic_cache/semantic_cache.py
upstash_semantic_cache-1.0.0.dist-info/LICENSE
upstash_semantic_cache-1.0.0.dist-info/METADATA
upstash_semantic_cache-1.0.0.dist-info/WHEEL
upstash_semantic_cache-1.0.0.dist-info/RECORD
