Metadata-Version: 2.1
Name: upstash-semantic-cache
Version: 1.0.0
Summary: Semantic Caching Algorithm for Upstash Vector
Home-page: https://github.com/upstash/semantic-cache-py
License: MIT
Keywords: Upstash,Upstash Vector,Semantic Cache
Author: Upstash
Author-email: support@upstash.com
Maintainer: Upstash
Maintainer-email: support@upstash.com
Requires-Python: >=3.8.1,<4.0
Classifier: Development Status :: 5 - Production/Stable
Classifier: Intended Audience :: Developers
Classifier: License :: OSI Approved :: MIT License
Classifier: Operating System :: OS Independent
Classifier: Programming Language :: Python
Classifier: Programming Language :: Python :: 3
Classifier: Programming Language :: Python :: 3.9
Classifier: Programming Language :: Python :: 3.10
Classifier: Programming Language :: Python :: 3.11
Classifier: Programming Language :: Python :: 3.12
Classifier: Programming Language :: Python :: 3 :: Only
Classifier: Programming Language :: Python :: 3.8
Classifier: Programming Language :: Python :: Implementation :: CPython
Classifier: Topic :: Database
Classifier: Topic :: Software Development :: Libraries
Requires-Dist: langchain_core (>=0.2.0,<0.3.0)
Requires-Dist: upstash_vector (>=0.5.0,<1)
Project-URL: Repository, https://github.com/upstash/semantic-cache-py
